{
    "Parameters": [
        {
            "Town": [
                "Town04"
            ],
            "approachSpeed": [
                10, 15
            ],
            "isRaining": [
                false
            ],
            "hourOfDay": [
                12
            ],
            "randomPosition": [
                true
            ],
            "initialOffset": [
                50, 70
            ],
            "repetitions": [
                10
            ],
            "npc_number": [
                20
            ],
            "check_lane": ["left"]
        }
    ]
}